{"plays":[{"turn":1,"cards_played":[],"current_player":"opponent","my_health":30,"opponent_health":0,"my_armor":0,"opponent_armor":0,"my_hand":1,"opponent_hand":0,"my_board":[],"opponent_board":[]},{"turn":2,"cards_played":["The Coin","Wild Growth"],"current_player":"me","my_health":30,"opponent_health":30,"my_armor":0,"opponent_armor":0,"my_hand":4,"opponent_hand":4,"my_board":[],"opponent_board":[]},{"turn":3,"cards_played":["Innervate","Piloted Shredder"],"current_player":"opponent","my_health":30,"opponent_health":30,"my_armor":0,"opponent_armor":0,"my_hand":4,"opponent_hand":3,"my_board":[],"opponent_board":[{"card_name":"Piloted Shredder","card_health":3,"card_attack":4}]},{"turn":4,"cards_played":["Wild Growth"],"current_player":"me","my_health":30,"opponent_health":30,"my_armor":0,"opponent_armor":0,"my_hand":4,"opponent_hand":3,"my_board":[],"opponent_board":[{"card_name":"Piloted Shredder","card_health":3,"card_attack":4}]},{"turn":5,"cards_played":["Shade of Naxxramas"],"current_player":"opponent","my_health":26,"opponent_health":30,"my_armor":0,"opponent_armor":0,"my_hand":4,"opponent_hand":3,"my_board":[],"opponent_board":[{"card_name":"Piloted Shredder","card_health":3,"card_attack":4},{"card_name":"Shade of Naxxramas","card_health":2,"card_attack":2}]},{"turn":6,"cards_played":["Azure Drake"],"current_player":"me","my_health":26,"opponent_health":30,"my_armor":0,"opponent_armor":0,"my_hand":5,"opponent_hand":3,"my_board":[{"card_name":"Azure Drake","card_health":4,"card_attack":4}],"opponent_board":[{"card_name":"Piloted Shredder","card_health":3,"card_attack":4},{"card_name":"Shade of Naxxramas","card_health":2,"card_attack":2}]},{"turn":7,"cards_played":["Shapeshift"],"current_player":"opponent","my_health":25,"opponent_health":30,"my_armor":0,"opponent_armor":1,"my_hand":5,"opponent_hand":4,"my_board":[],"opponent_board":[{"card_name":"Shade of Naxxramas","card_health":3,"card_attack":3},{"card_name":"Vitality Totem","card_health":3,"card_attack":0}]},{"turn":8,"cards_played":["Piloted Shredder","Darnassus Aspirant"],"current_player":"me","my_health":25,"opponent_health":30,"my_armor":0,"opponent_armor":1,"my_hand":4,"opponent_hand":4,"my_board":[{"card_name":"Darnassus Aspirant","card_health":3,"card_attack":2},{"card_name":"Piloted Shredder","card_health":3,"card_attack":4}],"opponent_board":[{"card_name":"Shade of Naxxramas","card_health":3,"card_attack":3},{"card_name":"Vitality Totem","card_health":3,"card_attack":0}]},{"turn":9,"cards_played":["Shapeshift"],"current_player":"opponent","my_health":24,"opponent_health":30,"my_armor":0,"opponent_armor":2,"my_hand":4,"opponent_hand":5,"my_board":[{"card_name":"Darnassus Aspirant","card_health":3,"card_attack":2},{"card_name":"Piloted Shredder","card_health":3,"card_attack":4}],"opponent_board":[{"card_name":"Shade of Naxxramas","card_health":4,"card_attack":4},{"card_name":"Vitality Totem","card_health":3,"card_attack":0}]},{"turn":10,"cards_played":["Ancient of War"],"current_player":"me","my_health":24,"opponent_health":30,"my_armor":0,"opponent_armor":0,"my_hand":4,"opponent_hand":5,"my_board":[{"card_name":"Ancient of War","card_health":10,"card_attack":5},{"card_name":"Darnassus Aspirant","card_health":3,"card_attack":2},{"card_name":"Piloted Shredder","card_health":3,"card_attack":4}],"opponent_board":[{"card_name":"Shade of Naxxramas","card_health":4,"card_attack":4}]},{"turn":11,"cards_played":["Shapeshift"],"current_player":"opponent","my_health":24,"opponent_health":30,"my_armor":0,"opponent_armor":1,"my_hand":4,"opponent_hand":6,"my_board":[{"card_name":"Ancient of War","card_health":10,"card_attack":5},{"card_name":"Darnassus Aspirant","card_health":3,"card_attack":2},{"card_name":"Piloted Shredder","card_health":3,"card_attack":4}],"opponent_board":[{"card_name":"Shade of Naxxramas","card_health":5,"card_attack":5}]},{"turn":12,"cards_played":["Force of Nature","Savage Roar"],"current_player":"me","my_health":24,"opponent_health":30,"my_armor":0,"opponent_armor":1,"my_hand":3,"opponent_hand":6,"my_board":[{"card_name":"Ancient of War","card_health":10,"card_attack":7},{"card_name":"Darnassus Aspirant","card_health":3,"card_attack":4},{"card_name":"Piloted Shredder","card_health":3,"card_attack":6},{"card_name":"Treant","card_health":2,"card_attack":4},{"card_name":"Treant","card_health":2,"card_attack":4},{"card_name":"Treant","card_health":2,"card_attack":4}],"opponent_board":[{"card_name":"Shade of Naxxramas","card_health":5,"card_attack":5}]}],"result":"victory"}