{"plays":[{"turn":1,"cards_played":[],"current_player":"me","my_health":0,"opponent_health":30,"my_armor":0,"opponent_armor":0,"my_hand":0,"opponent_hand":1,"my_board":[],"opponent_board":[]},{"turn":2,"cards_played":[],"current_player":"me","my_health":30,"opponent_health":30,"my_armor":0,"opponent_armor":0,"my_hand":6,"opponent_hand":4,"my_board":[],"opponent_board":[]},{"turn":3,"cards_played":["Mad Scientist"],"current_player":"opponent","my_health":30,"opponent_health":30,"my_armor":0,"opponent_armor":0,"my_hand":6,"opponent_hand":4,"my_board":[],"opponent_board":[{"card_name":"Mad Scientist","card_health":2,"card_attack":2}]},{"turn":4,"cards_played":["Backstab","Bloodmage Thalnos"],"current_player":"me","my_health":30,"opponent_health":30,"my_armor":0,"opponent_armor":0,"my_hand":5,"opponent_hand":4,"my_board":[{"card_name":"Bloodmage Thalnos","card_health":1,"card_attack":1}],"opponent_board":[{"card_name":"Bloodmage Thalnos","card_health":1,"card_attack":1}]},{"turn":5,"cards_played":["Fireblast","Fireblast"],"current_player":"opponent","my_health":29,"opponent_health":30,"my_armor":0,"opponent_armor":0,"my_hand":6,"opponent_hand":5,"my_board":[],"opponent_board":[{"card_name":"Bloodmage Thalnos","card_health":1,"card_attack":1}]},{"turn":6,"cards_played":["Dagger Mastery"],"current_player":"me","my_health":28,"opponent_health":30,"my_armor":0,"opponent_armor":0,"my_hand":7,"opponent_hand":6,"my_board":[],"opponent_board":[]},{"turn":7,"cards_played":["Sorcerer's Apprentice","Unstable Portal","Frostbolt"],"current_player":"opponent","my_health":28,"opponent_health":30,"my_armor":0,"opponent_armor":0,"my_hand":7,"opponent_hand":5,"my_board":[],"opponent_board":[{"card_name":"Sorcerer's Apprentice","card_health":2,"card_attack":3}]},{"turn":8,"cards_played":["Deathlord","The Coin","Eviscerate"],"current_player":"me","my_health":25,"opponent_health":30,"my_armor":0,"opponent_armor":0,"my_hand":5,"opponent_hand":5,"my_board":[{"card_name":"Deathlord","card_health":8,"card_attack":2}],"opponent_board":[]},{"turn":9,"cards_played":["Piloted Shredder"],"current_player":"opponent","my_health":25,"opponent_health":30,"my_armor":0,"opponent_armor":0,"my_hand":5,"opponent_hand":5,"my_board":[{"card_name":"Deathlord","card_health":8,"card_attack":2}],"opponent_board":[{"card_name":"Piloted Shredder","card_health":3,"card_attack":4}]},{"turn":10,"cards_played":["Coldlight Oracle","Gang Up"],"current_player":"me","my_health":25,"opponent_health":28,"my_armor":0,"opponent_armor":0,"my_hand":6,"opponent_hand":7,"my_board":[{"card_name":"Coldlight Oracle","card_health":2,"card_attack":2},{"card_name":"Deathlord","card_health":8,"card_attack":2}],"opponent_board":[{"card_name":"Piloted Shredder","card_health":3,"card_attack":4}]},{"turn":11,"cards_played":["Fireball","Fireblast","Fireblast"],"current_player":"opponent","my_health":24,"opponent_health":28,"my_armor":0,"opponent_armor":0,"my_hand":6,"opponent_hand":7,"my_board":[{"card_name":"Coldlight Oracle","card_health":2,"card_attack":2}],"opponent_board":[{"card_name":"Mad Scientist","card_health":2,"card_attack":2},{"card_name":"Piloted Shredder","card_health":1,"card_attack":4}]},{"turn":12,"cards_played":["Shadowstep","Coldlight Oracle","Preparation","Vanish","Dagger Mastery"],"current_player":"me","my_health":24,"opponent_health":25,"my_armor":0,"opponent_armor":0,"my_hand":7,"opponent_hand":10,"my_board":[],"opponent_board":[]},{"turn":13,"cards_played":["Flamewaker","Piloted Shredder"],"current_player":"opponent","my_health":24,"opponent_health":25,"my_armor":0,"opponent_armor":0,"my_hand":7,"opponent_hand":8,"my_board":[],"opponent_board":[{"card_name":"Flamewaker","card_health":4,"card_attack":2},{"card_name":"Piloted Shredder","card_health":3,"card_attack":4}]},{"turn":14,"cards_played":["Coldlight Oracle","Coldlight Oracle","Backstab"],"current_player":"me","my_health":20,"opponent_health":25,"my_armor":0,"opponent_armor":0,"my_hand":9,"opponent_hand":10,"my_board":[{"card_name":"Coldlight Oracle","card_health":2,"card_attack":2},{"card_name":"Coldlight Oracle","card_health":2,"card_attack":2}],"opponent_board":[{"card_name":"Flamewaker","card_health":4,"card_attack":2},{"card_name":"Ethereal Arcanist","card_health":3,"card_attack":3},{"card_name":"Succubus","card_health":3,"card_attack":4}]},{"turn":15,"cards_played":["Mana Wyrm","Arcane Blast","Frostbolt","Fireblast","Fireblast"],"current_player":"opponent","my_health":5,"opponent_health":25,"my_armor":0,"opponent_armor":0,"my_hand":9,"opponent_hand":7,"my_board":[],"opponent_board":[{"card_name":"Flamewaker","card_health":4,"card_attack":2},{"card_name":"Mana Wyrm","card_health":3,"card_attack":3},{"card_name":"Ethereal Arcanist","card_health":3,"card_attack":3},{"card_name":"Succubus","card_health":3,"card_attack":4}]},{"turn":16,"cards_played":["Coldlight Oracle","Fan of Knives","Gang Up"],"current_player":"me","my_health":5,"opponent_health":25,"my_armor":0,"opponent_armor":0,"my_hand":9,"opponent_hand":9,"my_board":[{"card_name":"Coldlight Oracle","card_health":2,"card_attack":2}],"opponent_board":[{"card_name":"Flamewaker","card_health":3,"card_attack":2},{"card_name":"Mana Wyrm","card_health":2,"card_attack":3},{"card_name":"Ethereal Arcanist","card_health":2,"card_attack":3},{"card_name":"Succubus","card_health":2,"card_attack":4}]}],"result":"defeat"}