{"plays":[{"turn":1,"cards_played":[],"current_player":"opponent","my_health":0,"opponent_health":0,"my_armor":0,"opponent_armor":0,"my_hand":4,"opponent_hand":1,"my_board":[],"opponent_board":[]},{"turn":2,"cards_played":["Tunnel Trogg","The Coin","Wyrmrest Agent"],"current_player":"me","my_health":30,"opponent_health":30,"my_armor":0,"opponent_armor":0,"my_hand":4,"opponent_hand":3,"my_board":[{"card_name":"Wyrmrest Agent","card_health":4,"card_attack":1}],"opponent_board":[{"card_name":"Tunnel Trogg","card_health":3,"card_attack":1}]},{"turn":3,"cards_played":["Rockbiter Weapon"],"current_player":"opponent","my_health":30,"opponent_health":30,"my_armor":0,"opponent_armor":0,"my_hand":4,"opponent_hand":3,"my_board":[],"opponent_board":[{"card_name":"Tunnel Trogg","card_health":1,"card_attack":4}]},{"turn":4,"cards_played":["Lesser Heal","Lesser Heal"],"current_player":"me","my_health":30,"opponent_health":30,"my_armor":0,"opponent_armor":0,"my_hand":5,"opponent_hand":3,"my_board":[],"opponent_board":[{"card_name":"Tunnel Trogg","card_health":1,"card_attack":1}]},{"turn":5,"cards_played":["Tunnel Trogg","Totemic Call"],"current_player":"opponent","my_health":29,"opponent_health":30,"my_armor":0,"opponent_armor":0,"my_hand":5,"opponent_hand":3,"my_board":[],"opponent_board":[{"card_name":"Tunnel Trogg","card_health":3,"card_attack":1},{"card_name":"Tunnel Trogg","card_health":1,"card_attack":1},{"card_name":"Searing Totem","card_health":1,"card_attack":1}]},{"turn":6,"cards_played":["Blackwing Technician"],"current_player":"me","my_health":29,"opponent_health":30,"my_armor":0,"opponent_armor":0,"my_hand":5,"opponent_hand":3,"my_board":[{"card_name":"Blackwing Technician","card_health":4,"card_attack":2}],"opponent_board":[{"card_name":"Tunnel Trogg","card_health":3,"card_attack":1},{"card_name":"Tunnel Trogg","card_health":1,"card_attack":1},{"card_name":"Searing Totem","card_health":1,"card_attack":1}]},{"turn":7,"cards_played":["Draenei Totemcarver"],"current_player":"opponent","my_health":26,"opponent_health":30,"my_armor":0,"opponent_armor":0,"my_hand":5,"opponent_hand":3,"my_board":[{"card_name":"Blackwing Technician","card_health":5,"card_attack":3}],"opponent_board":[{"card_name":"Draenei Totemcarver","card_health":5,"card_attack":5},{"card_name":"Tunnel Trogg","card_health":3,"card_attack":1},{"card_name":"Tunnel Trogg","card_health":1,"card_attack":1},{"card_name":"Searing Totem","card_health":1,"card_attack":1}]},{"turn":8,"cards_played":["Blackwing Technician"],"current_player":"me","my_health":26,"opponent_health":30,"my_armor":0,"opponent_armor":0,"my_hand":5,"opponent_hand":3,"my_board":[{"card_name":"Blackwing Technician","card_health":5,"card_attack":3},{"card_name":"Blackwing Technician","card_health":4,"card_attack":3}],"opponent_board":[{"card_name":"Draenei Totemcarver","card_health":5,"card_attack":5},{"card_name":"Tunnel Trogg","card_health":1,"card_attack":1},{"card_name":"Searing Totem","card_health":1,"card_attack":1}]},{"turn":9,"cards_played":["Thunder Bluff Valiant"],"current_player":"opponent","my_health":24,"opponent_health":30,"my_armor":0,"opponent_armor":0,"my_hand":5,"opponent_hand":3,"my_board":[{"card_name":"Blackwing Technician","card_health":4,"card_attack":3}],"opponent_board":[{"card_name":"Draenei Totemcarver","card_health":2,"card_attack":5},{"card_name":"Tunnel Trogg","card_health":1,"card_attack":1},{"card_name":"Thunder Bluff Valiant","card_health":6,"card_attack":3},{"card_name":"Searing Totem","card_health":1,"card_attack":1}]},{"turn":10,"cards_played":["Holy Nova"],"current_player":"me","my_health":26,"opponent_health":28,"my_armor":0,"opponent_armor":0,"my_hand":5,"opponent_hand":3,"my_board":[{"card_name":"Blackwing Technician","card_health":3,"card_attack":3}],"opponent_board":[{"card_name":"Thunder Bluff Valiant","card_health":1,"card_attack":3}]},{"turn":11,"cards_played":["Totemic Call","Feral Spirit"],"current_player":"opponent","my_health":23,"opponent_health":28,"my_armor":0,"opponent_armor":0,"my_hand":5,"opponent_hand":3,"my_board":[{"card_name":"Blackwing Technician","card_health":3,"card_attack":3}],"opponent_board":[{"card_name":"Thunder Bluff Valiant","card_health":1,"card_attack":3},{"card_name":"Stoneclaw Totem","card_health":2,"card_attack":2},{"card_name":"Spirit Wolf","card_health":3,"card_attack":2},{"card_name":"Spirit Wolf","card_health":3,"card_attack":2}]},{"turn":12,"cards_played":["Shadow Word: Pain","Lesser Heal","Lesser Heal"],"current_player":"me","my_health":23,"opponent_health":28,"my_armor":0,"opponent_armor":0,"my_hand":5,"opponent_hand":3,"my_board":[{"card_name":"Blackwing Technician","card_health":3,"card_attack":3}],"opponent_board":[{"card_name":"Stoneclaw Totem","card_health":2,"card_attack":2},{"card_name":"Spirit Wolf","card_health":3,"card_attack":2}]},{"turn":13,"cards_played":["Mana Tide Totem","Flame Juggler"],"current_player":"opponent","my_health":21,"opponent_health":28,"my_armor":0,"opponent_armor":0,"my_hand":5,"opponent_hand":3,"my_board":[],"opponent_board":[{"card_name":"Flame Juggler","card_health":3,"card_attack":2},{"card_name":"Mana Tide Totem","card_health":3,"card_attack":0},{"card_name":"Spirit Wolf","card_health":3,"card_attack":2}]},{"turn":14,"cards_played":["Blackwing Corruptor","Lesser Heal","Lesser Heal"],"current_player":"me","my_health":23,"opponent_health":28,"my_armor":0,"opponent_armor":0,"my_hand":5,"opponent_hand":3,"my_board":[{"card_name":"Blackwing Corruptor","card_health":4,"card_attack":5}],"opponent_board":[{"card_name":"Flame Juggler","card_health":3,"card_attack":2},{"card_name":"Spirit Wolf","card_health":3,"card_attack":2}]},{"turn":15,"cards_played":["Al'Akir the Windlord"],"current_player":"opponent","my_health":18,"opponent_health":28,"my_armor":0,"opponent_armor":0,"my_hand":5,"opponent_hand":3,"my_board":[],"opponent_board":[{"card_name":"Al'Akir the Windlord","card_health":5,"card_attack":3},{"card_name":"Spirit Wolf","card_health":3,"card_attack":2}]},{"turn":16,"cards_played":["Blackwing Corruptor","Lesser Heal"],"current_player":"me","my_health":20,"opponent_health":28,"my_armor":0,"opponent_armor":0,"my_hand":5,"opponent_hand":3,"my_board":[{"card_name":"Blackwing Corruptor","card_health":4,"card_attack":5}],"opponent_board":[{"card_name":"Al'Akir the Windlord","card_health":5,"card_attack":3}]},{"turn":17,"cards_played":["Hex","Totemic Call","Master of Evolution"],"current_player":"opponent","my_health":17,"opponent_health":28,"my_armor":0,"opponent_armor":0,"my_hand":5,"opponent_hand":2,"my_board":[],"opponent_board":[{"card_name":"Al'Akir the Windlord","card_health":5,"card_attack":3},{"card_name":"Master of Evolution","card_health":5,"card_attack":4},{"card_name":"Wrath of Air Totem","card_health":2,"card_attack":0},{"card_name":"Bloodfen Raptor","card_health":2,"card_attack":3}]},{"turn":18,"cards_played":["Azure Drake","Twilight Guardian"],"current_player":"me","my_health":17,"opponent_health":28,"my_armor":0,"opponent_armor":0,"my_hand":5,"opponent_hand":2,"my_board":[{"card_name":"Azure Drake","card_health":4,"card_attack":4},{"card_name":"Twilight Guardian","card_health":6,"card_attack":2}],"opponent_board":[{"card_name":"Al'Akir the Windlord","card_health":5,"card_attack":3},{"card_name":"Master of Evolution","card_health":5,"card_attack":4},{"card_name":"Bloodfen Raptor","card_health":2,"card_attack":3}]},{"turn":19,"cards_played":["Totemic Call","Lightning Storm","Master of Evolution"],"current_player":"opponent","my_health":11,"opponent_health":28,"my_armor":0,"opponent_armor":0,"my_hand":5,"opponent_hand":1,"my_board":[],"opponent_board":[{"card_name":"Al'Akir the Windlord","card_health":5,"card_attack":3},{"card_name":"Master of Evolution","card_health":5,"card_attack":4},{"card_name":"Master of Evolution","card_health":2,"card_attack":4},{"card_name":"Stoneclaw Totem","card_health":2,"card_attack":0},{"card_name":"Hallazeal the Ascended","card_health":6,"card_attack":4}]},{"turn":20,"cards_played":["Museum Curator","Azure Drake","Wyrmrest Agent","Twilight Whelp"],"current_player":"me","my_health":11,"opponent_health":28,"my_armor":0,"opponent_armor":0,"my_hand":4,"opponent_hand":1,"my_board":[{"card_name":"Azure Drake","card_health":4,"card_attack":4},{"card_name":"Museum Curator","card_health":2,"card_attack":1},{"card_name":"Twilight Whelp","card_health":1,"card_attack":2},{"card_name":"Wyrmrest Agent","card_health":4,"card_attack":2}],"opponent_board":[{"card_name":"Al'Akir the Windlord","card_health":5,"card_attack":3},{"card_name":"Master of Evolution","card_health":5,"card_attack":4},{"card_name":"Stoneclaw Totem","card_health":2,"card_attack":0},{"card_name":"Hallazeal the Ascended","card_health":6,"card_attack":4}]},{"turn":21,"cards_played":["Totemic Call","Totem Golem"],"current_player":"opponent","my_health":5,"opponent_health":28,"my_armor":0,"opponent_armor":0,"my_hand":4,"opponent_hand":1,"my_board":[{"card_name":"Museum Curator","card_health":2,"card_attack":1},{"card_name":"Twilight Whelp","card_health":3,"card_attack":2}],"opponent_board":[{"card_name":"Totem Golem","card_health":4,"card_attack":3},{"card_name":"Al'Akir the Windlord","card_health":5,"card_attack":3},{"card_name":"Master of Evolution","card_health":1,"card_attack":4},{"card_name":"Stoneclaw Totem","card_health":2,"card_attack":0},{"card_name":"Hallazeal the Ascended","card_health":4,"card_attack":4},{"card_name":"Healing Totem","card_health":2,"card_attack":0}]},{"turn":22,"cards_played":["Shadow Word: Pain","Abomination","Lesser Heal"],"current_player":"me","my_health":7,"opponent_health":28,"my_armor":0,"opponent_armor":0,"my_hand":3,"opponent_hand":1,"my_board":[{"card_name":"Museum Curator","card_health":2,"card_attack":1},{"card_name":"Twilight Whelp","card_health":3,"card_attack":2},{"card_name":"Abomination","card_health":4,"card_attack":4}],"opponent_board":[{"card_name":"Totem Golem","card_health":4,"card_attack":3},{"card_name":"Master of Evolution","card_health":2,"card_attack":4},{"card_name":"Hallazeal the Ascended","card_health":5,"card_attack":4},{"card_name":"Healing Totem","card_health":2,"card_attack":0}]}],"result":"defeat"}